portfolio_performance/__init__.py
portfolio_performance/src/__init__.py
portfolio_performance/src/app.py
portfolio_performance/src/model.py
portfolio_performance/src/modelGamma.py
portfolio_performance/src/modelGammaSigma.py
portfolio_performance/src/modelNoGamma.py
portfolio_performance/src/models/JagannathanMa.py
portfolio_performance/src/models/__init__.py
portfolio_performance/src/models/bayesStein.py
portfolio_performance/src/models/bayesSteinShortSellCon.py
portfolio_performance/src/models/bayesianDataModel.py
portfolio_performance/src/models/ew.py
portfolio_performance/src/models/kanZhou.py
portfolio_performance/src/models/kanZhouEw.py
portfolio_performance/src/models/macKinlayPastor.py
portfolio_performance/src/models/meanVar.py
portfolio_performance/src/models/meanVarShortSellCon.py
portfolio_performance/src/models/minVar.py
portfolio_performance/src/models/minVarShortSellCon.py
portfolio_performance/src/utils/__init__.py
portfolio_performance/src/utils/filter.py
portfolio_performance/src/utils/quadprog.py
portfolio_performance/src/utils/sharedOptions.py
portfolio_performance/src/utils/statistics.py
portfolio_performance-1.0.3.dist-info/METADATA
portfolio_performance-1.0.3.dist-info/WHEEL
portfolio_performance-1.0.3.dist-info/top_level.txt
portfolio_performance-1.0.3.dist-info/RECORD
